speech_tension_detector/__init__.py
speech_tension_detector/cli.py
speech_tension_detector/analyzers/__init__.py
speech_tension_detector/analyzers/advanced_vocal_effort.py
speech_tension_detector/analyzers/glottal_source_analysis.py
speech_tension_detector/analyzers/prosodic_features.py
speech_tension_detector/analyzers/quality_separation.py
speech_tension_detector/analyzers/spectral_analysis.py
speech_tension_detector/analyzers/wavelet_fractal_analysis.py
speech_tension_detector/classifiers/__init__.py
speech_tension_detector/classifiers/advanced_signal.py
speech_tension_detector/classifiers/ml_feature_extractor.py
speech_tension_detector/classifiers/pretrained_model.py
speech_tension_detector/core/__init__.py
speech_tension_detector/core/detector.py
speech_tension_detector/core/parallel_batch.py
speech_tension_detector/core/speed_optimized.py
speech_tension_detector/utils/__init__.py
speech_tension_detector-1.0.2.dist-info/licenses/LICENSE
speech_tension_detector-1.0.2.dist-info/METADATA
speech_tension_detector-1.0.2.dist-info/WHEEL
speech_tension_detector-1.0.2.dist-info/entry_points.txt
speech_tension_detector-1.0.2.dist-info/top_level.txt
speech_tension_detector-1.0.2.dist-info/RECORD
