Metadata-Version: 2.4
Name: speech-tension-detector
Version: 1.0.2
Summary: 音声ファイルから話者の緊張度・テンションを検出するPythonモジュール
Home-page: https://github.com/hiroshi-tamura/speech-tension-detector
Author: hiroshi-tamura
Author-email: hiroshi.tamura.dev@example.com
License: MIT
Keywords: speech,audio,tension,detection,machine-learning
Classifier: Development Status :: 4 - Beta
Classifier: Intended Audience :: Developers
Classifier: Intended Audience :: Science/Research
Classifier: License :: OSI Approved :: MIT License
Classifier: Operating System :: Microsoft :: Windows
Classifier: Programming Language :: Python :: 3
Classifier: Programming Language :: Python :: 3.8
Classifier: Programming Language :: Python :: 3.9
Classifier: Programming Language :: Python :: 3.10
Classifier: Programming Language :: Python :: 3.11
Classifier: Topic :: Multimedia :: Sound/Audio :: Analysis
Classifier: Topic :: Scientific/Engineering :: Artificial Intelligence
Requires-Python: >=3.8
License-File: LICENSE
Requires-Dist: librosa>=0.10.0
Requires-Dist: soundfile>=0.12.1
Requires-Dist: numpy>=1.20.0
Requires-Dist: scipy>=1.8.0
Requires-Dist: scikit-learn>=1.0.0
Requires-Dist: tqdm>=4.60.0
Requires-Dist: PyWavelets>=1.4.0
Provides-Extra: full
Requires-Dist: torch>=2.0.0; extra == "full"
Requires-Dist: transformers>=4.30.0; extra == "full"
Requires-Dist: pandas>=2.0.0; extra == "full"
Requires-Dist: matplotlib>=3.7.0; extra == "full"
Provides-Extra: prosodic
Requires-Dist: praat-parselmouth>=0.4.3; extra == "prosodic"
Provides-Extra: gpu
Requires-Dist: torch>=2.0.0; extra == "gpu"
Requires-Dist: transformers>=4.30.0; extra == "gpu"
Requires-Dist: accelerate>=0.21.0; extra == "gpu"
Provides-Extra: advanced
Requires-Dist: opensmile>=2.5.0; extra == "advanced"
Requires-Dist: tensorflow>=2.13.0; extra == "advanced"
Requires-Dist: datasets>=2.14.0; extra == "advanced"
Provides-Extra: dev
Requires-Dist: pytest>=7.0.0; extra == "dev"
Requires-Dist: pytest-cov>=4.0.0; extra == "dev"
Requires-Dist: black>=23.0.0; extra == "dev"
Requires-Dist: flake8>=6.0.0; extra == "dev"
Requires-Dist: mypy>=1.0.0; extra == "dev"
Dynamic: author-email
Dynamic: home-page
Dynamic: license-file
Dynamic: requires-python
